Metadata-Version: 1.2
Name: python-itaushopline
Version: 1.0.2
Summary: Lib para consultas e pagamentos via Itaú Shopline.
Home-page: https://github.com/MrPowerUp82/python_itaushopline
Author: MrPowerUp
Author-email: gustavohenrique8282@hotmail.com
License: MIT
Project-URL: Código fonte, https://github.com/MrPowerUp82/python_itaushopline
Keywords: API ItaúShopline Itaú
Platform: UNKNOWN
Classifier: Development Status :: 5 - Production/Stable
Classifier: Intended Audience :: Developers
Classifier: License :: OSI Approved :: MIT License
Classifier: Natural Language :: Portuguese (Brazilian)
Classifier: Operating System :: OS Independent
Classifier: Topic :: Software Development :: Internationalization
Classifier: Topic :: Scientific/Engineering :: Physics
